[{"BANK":"A P MAHESH CO-OP URBAN BANK LTD.","IFSC":"APMC0000001","BRANCH":"HEAD OFFICE","CENTRE":"HYDERABAD","DISTRICT":"HYDERABAD","STATE":"ANDHRA PRADESH","ADDRESS":"5-3-989,3RD FLOOR, SHERZA ESTATE, N.S. ROAD, OSMANGUNJ, HYDERABAD - 500 095","CONTACT":"23437100","IMPS":true,"RTGS":true,"NEFT":false,"MICR":null,"bankSlug":"a-p-mahesh-coop-urban-bank-ltd","stateSlug":"andhra-pradesh","citySlug":"hyderabad","branchSlug":"head-office","type":"IfscJson"},{"IFSC":"APMC0000002","BRANCH":"BEGUM BAZAR","CENTRE":"HYDERABAD","DISTRICT":"HYDERABAD","STATE":"ANDHRA PRADESH","ADDRESS":"15-7-241/1, YADAV TOWERS BEGUM BAZAR HYD 500012","CONTACT":"23437131","BANK":"THE A.P. MAHESH COOPERATIVE URBAN BANK LIMITED","RTGS":true,"CITY":"HYDERABAD","NEFT":true,"IMPS":true,"MICR":null,"bankSlug":"the-ap-mahesh-cooperative-urban-bank-limited","stateSlug":"andhra-pradesh","citySlug":"hyderabad","branchSlug":"begum-bazar","type":"IfscJson"},{"IFSC":"APMC0000003","BRANCH":"BALANAGAR","CENTRE":"HYDERABAD","DISTRICT":"HYDERABAD","STATE":"ANDHRA PRADESH","ADDRESS":"3-66, SHOBHANA COMPLEX BALANAGAR HYD -37","CONTACT":"23770307","BANK":"THE A.P. MAHESH COOPERATIVE URBAN BANK LIMITED","RTGS":true,"CITY":"RANGA REDDY","NEFT":true,"IMPS":true,"MICR":null,"bankSlug":"the-ap-mahesh-cooperative-urban-bank-limited","stateSlug":"andhra-pradesh","citySlug":"ranga-reddy","branchSlug":"balanagar","type":"IfscJson"},{"IFSC":"APMC0000004","BRANCH":"KHAIRTABAD","CENTRE":"HYDERABAD","DISTRICT":"HYDERABAD","STATE":"ANDHRA PRADESH","ADDRESS":"6-1-1060 HAFEZ COMPLEX SAIFABAD HYD - 500004","CONTACT":"23431801","BANK":"THE A.P. MAHESH COOPERATIVE URBAN BANK LIMITED","RTGS":true,"CITY":"HYDERABAD","NEFT":true,"IMPS":true,"MICR":null,"bankSlug":"the-ap-mahesh-cooperative-urban-bank-limited","stateSlug":"andhra-pradesh","citySlug":"hyderabad","branchSlug":"khairtabad","type":"IfscJson"},{"IFSC":"APMC0000005","BRANCH":"SHAMSHEER GUNJ","CENTRE":"HYDERABAD","DISTRICT":"HYDERABAD","STATE":"ANDHRA PRADESH","ADDRESS":"18-4-568 MAIN ROAD SHAMSHEER GUNJ HYD - 253","CONTACT":"23437110","BANK":"THE A.P. MAHESH COOPERATIVE URBAN BANK LIMITED","RTGS":true,"CITY":"HYDERABAD","NEFT":true,"IMPS":true,"MICR":null,"bankSlug":"the-ap-mahesh-cooperative-urban-bank-limited","stateSlug":"andhra-pradesh","citySlug":"hyderabad","branchSlug":"shamsheer-gunj","type":"IfscJson"}]