[{"IFSC":"HDFC0000001","BRANCH":"TULSIANI CHMBRS - NARIMAN PT","CENTRE":"MUMBAI","DISTRICT":"MUMBAI","STATE":"MAHARASHTRA","ADDRESS":"101-104 TULSIANI CHAMBERSFREE PRESS JOURNAL MARGNARIMAN POINTMUMBAIMAHARASHTRA400 021","CONTACT":"9890603333","MICR":"400240003","BANK":"HDFC BANK","RTGS":true,"CITY":"GREATER MUMBAI","NEFT":true,"IMPS":true,"bankSlug":"hdfc-bank","stateSlug":"maharashtra","citySlug":"greater-mumbai","branchSlug":"tulsiani-chmbrs-nariman-pt","type":"IfscJson"},{"IFSC":"HDFC0000002","BRANCH":"MUMBAI - KHAR (WEST)","CENTRE":"MUMBAI","DISTRICT":"MUMBAI","STATE":"MAHARASHTRA","ADDRESS":"SWAGATAM,OPP. KHAR POLICE STATION,S.V.ROAD, KHAR (WEST)MUMBAIMAHARASHTRA400 052","CONTACT":"9890603333","MICR":"400240004","BANK":"HDFC BANK","RTGS":true,"CITY":"GREATER MUMBAI","NEFT":true,"IMPS":true,"bankSlug":"hdfc-bank","stateSlug":"maharashtra","citySlug":"greater-mumbai","branchSlug":"mumbai-khar-west","type":"IfscJson"},{"IFSC":"HDFC0000003","BRANCH":"K G MARG","CENTRE":"DELHI","DISTRICT":"DELHI","STATE":"DELHI","ADDRESS":"209 - 214, KAILASH BUILDING, 26, KASTURBA GANDHI MARG, NEW DELHI 110001","CONTACT":"61606161","MICR":"110240001","BANK":"HDFC BANK","RTGS":true,"CITY":"NEW DELHI","NEFT":true,"IMPS":true,"bankSlug":"hdfc-bank","stateSlug":"delhi","citySlug":"new-delhi","branchSlug":"k-g-marg","type":"IfscJson"},{"IFSC":"HDFC0000004","BRANCH":"CHENNAI - ITC CENTRE - ANNA SALAI","CENTRE":"CHENNAI","DISTRICT":"CHENNAI","STATE":"TAMIL NADU","ADDRESS":"759, ITC CENTREANNA SALAI, OPP T.V.S.CHENNAITAMILNADU600 002","CONTACT":"9840673333","MICR":"600240002","BANK":"HDFC BANK","RTGS":true,"CITY":"CHENNAI","NEFT":true,"IMPS":true,"bankSlug":"hdfc-bank","stateSlug":"tamil-nadu","citySlug":"chennai","branchSlug":"chennai-itc-centre-anna-salai","type":"IfscJson"},{"IFSC":"HDFC0000005","BRANCH":"BHULABHAI DESAI ROAD","CENTRE":"MUMBAI","DISTRICT":"MUMBAI","STATE":"MAHARASHTRA","ADDRESS":"HDFC BANK LTD 36 VALLABH APTS 87 BHULABHAI DESAI ROAD MUMBAI MAHARASHTRA 400026","CONTACT":"61606161","MICR":"400240005","BANK":"HDFC BANK","RTGS":true,"CITY":"GREATER MUMBAI","NEFT":true,"IMPS":true,"bankSlug":"hdfc-bank","stateSlug":"maharashtra","citySlug":"greater-mumbai","branchSlug":"bhulabhai-desai-road","type":"IfscJson"}]