[{"IFSC":"KOLH0000001","BRANCH":"HEAD OFFICE","CENTRE":"KOLHAPUR","DISTRICT":"OHPR","STATE":"MAHARASHTRA","ADDRESS":"514,D WARD GANGAWESH 1ST FLOOR KOLHAPUR 416002","CONTACT":"02312547242","BANK":"THE KOLHAPUR URBAN CO-OP. BANK LTD.","RTGS":true,"NEFT":false,"IMPS":true,"MICR":null,"bankSlug":"the-kolhapur-urban-coop-bank-ltd","stateSlug":"maharashtra","citySlug":"kolhapur","branchSlug":"head-office","type":"IfscJson"},{"IFSC":"KOLH0000003","BRANCH":"MAIN BRANCH","CENTRE":"KOLHAPUR","DISTRICT":"OHPR","STATE":"MAHARASHTRA","ADDRESS":"514,D WARD,GANGAWESH,GROUND FLOOR,KOLHAPUR 416002","CONTACT":"02312547248","MICR":"416398003","BANK":"THE KOLHAPUR URBAN CO-OP. BANK LTD.","RTGS":true,"NEFT":false,"IMPS":true,"bankSlug":"the-kolhapur-urban-coop-bank-ltd","stateSlug":"maharashtra","citySlug":"kolhapur","branchSlug":"main-branch","type":"IfscJson"},{"IFSC":"KOLH0000004","BRANCH":"RAJARAMPURI BRANCH","CENTRE":"KOLHAPUR","DISTRICT":"OHPR","STATE":"MAHARASHTRA","ADDRESS":"1866 E WARD,RAJARAMPURI,7TH LANE,KOLHAPUR-416008","CONTACT":"02312534924","MICR":"416398004","BANK":"THE KOLHAPUR URBAN CO-OP. BANK LTD.","RTGS":true,"NEFT":false,"IMPS":true,"bankSlug":"the-kolhapur-urban-coop-bank-ltd","stateSlug":"maharashtra","citySlug":"kolhapur","branchSlug":"rajarampuri-branch","type":"IfscJson"},{"IFSC":"KOLH0000005","BRANCH":"NEW SHAHUPURI BRANCH","CENTRE":"KOLHAPUR","DISTRICT":"OHPR","STATE":"MAHARASHTRA","ADDRESS":"329 E WARD,STATION ROAD,NEW SHAHUPURI,KOLHAPUR.416003","CONTACT":"02312661940","MICR":"416398005","BANK":"THE KOLHAPUR URBAN CO-OP. BANK LTD.","RTGS":true,"NEFT":false,"IMPS":true,"bankSlug":"the-kolhapur-urban-coop-bank-ltd","stateSlug":"maharashtra","citySlug":"kolhapur","branchSlug":"new-shahupuri-branch","type":"IfscJson"},{"IFSC":"KOLH0000006","BRANCH":"MARKET YARD BRANCH","CENTRE":"KOLHAPUR","DISTRICT":"OHPR","STATE":"MAHARASHTRA","ADDRESS":"SHRI SHAHU MARKET YARD,KOLHAPUR.416005","CONTACT":"02312657731","MICR":"416398006","BANK":"THE KOLHAPUR URBAN CO-OP. BANK LTD.","RTGS":true,"NEFT":false,"IMPS":true,"bankSlug":"the-kolhapur-urban-coop-bank-ltd","stateSlug":"maharashtra","citySlug":"kolhapur","branchSlug":"market-yard-branch","type":"IfscJson"}]